zamg/__init__.py
zamg/exceptions.py
zamg/zamg.py
zamg-0.3.6.dist-info/LICENSE
zamg-0.3.6.dist-info/METADATA
zamg-0.3.6.dist-info/WHEEL
zamg-0.3.6.dist-info/RECORD
