Metadata-Version: 2.1
Name: zamg
Version: 0.3.6
Summary: Asynchronous Python client for GeoSphere Austria (ZAMG) weather data.
Home-page: https://github.com/killer0071234/python-zamg
License: MIT
Keywords: geosphere,zamg,api,async,client
Author: Daniel Gangl
Author-email: killer007@gmx.at
Maintainer: Daniel Gangl
Maintainer-email: killer007@gmx.at
Requires-Python: >=3.8,<4.0
Classifier: Development Status :: 4 - Beta
Classifier: Framework :: AsyncIO
Classifier: Intended Audience :: Developers
Classifier: License :: OSI Approved :: MIT License
Classifier: Natural Language :: English
Classifier: Programming Language :: Python :: 3
Classifier: Programming Language :: Python :: 3.8
Classifier: Programming Language :: Python :: 3.9
Classifier: Programming Language :: Python :: 3.10
Classifier: Programming Language :: Python :: 3.11
Classifier: Programming Language :: Python :: 3.12
Classifier: Topic :: Software Development :: Libraries :: Python Modules
Requires-Dist: aiohttp (>=3.8.0)
Requires-Dist: async-timeout (>=4.0.3,<5.0.0)
Project-URL: Bug Tracker, https://github.com/killer0071234/python-zamg/issues
Project-URL: Changelog, https://github.com/killer0071234/python-zamg/releases
Project-URL: Documentation, https://github.com/killer0071234/python-zamg
Project-URL: Repository, https://github.com/killer0071234/python-zamg
